pyFlowSOM/cyFlowSOM.cpython-310-aarch64-linux-gnu.so
pyFlowSOM/.gitignore
pyFlowSOM/cyFlowSOM.c
pyFlowSOM/cyFlowSOM.pyx
pyFlowSOM/flowsom.c
pyFlowSOM/__init__.py
pyFlowSOM-0.1.16.dist-info/RECORD
pyFlowSOM-0.1.16.dist-info/top_level.txt
pyFlowSOM-0.1.16.dist-info/LICENSE
pyFlowSOM-0.1.16.dist-info/WHEEL
pyFlowSOM-0.1.16.dist-info/METADATA
