Metadata-Version: 2.1
Name: pyFlowSOM
Version: 0.1.16
Summary: A Python implementation of the SOM training functionality of FlowSOM
Author-email: Angelo Lab <theangelolab@gmail.com>
License: Modified Apache License 2.0
Project-URL: repository, https://github.com/angelolab/pyFlowSOM
Classifier: Development Status :: 4 - Beta
Classifier: Programming Language :: Cython
Classifier: Programming Language :: Python :: 3
Classifier: Programming Language :: Python :: 3.9
Classifier: Programming Language :: Python :: 3.10
Classifier: Programming Language :: Python :: 3.11
Classifier: Programming Language :: Python :: 3.12
Classifier: License :: OSI Approved :: Apache Software License
Classifier: Topic :: Scientific/Engineering :: Bio-Informatics
Requires-Python: >=3.9
License-File: LICENSE
Requires-Dist: Cython>=3
Requires-Dist: numpy<2,>=1
Requires-Dist: scipy<2,>=1
Provides-Extra: test
Requires-Dist: pytest; extra == "test"
Requires-Dist: pytest-cases; extra == "test"
Requires-Dist: pytest-cov; extra == "test"
Requires-Dist: pytest-mock; extra == "test"
Requires-Dist: pytest-pycodestyle; extra == "test"
Requires-Dist: pytest-randomly; extra == "test"
Requires-Dist: seaborn; extra == "test"
Requires-Dist: pandas; extra == "test"
